pyvi_editor/__init__.py
pyvi_editor/autocomplete.py
pyvi_editor/components/__init__.py
pyvi_editor/components/delete_dialog.py
pyvi_editor/components/directory_content_text.py
pyvi_editor/components/footer.py
pyvi_editor/components/header.py
pyvi_editor/components/main_editor.py
pyvi_editor/components/search_file_dialog.py
pyvi_editor/components/sidebar.py
pyvi_editor/components/sidebar_input.py
pyvi_editor/components/text_area.py
pyvi_editor/components/welcome_text.py
pyvi_editor/editor.py
pyvi_editor/highlight_query/c_highlights.scm
pyvi_editor/highlight_query/cpp_highlights.scm
pyvi_editor/highlight_query/java_highlights.scm
pyvi_editor/highlight_query/javascript_highlights.scm
pyvi_editor/highlight_query/php_highlights.scm
pyvi_editor/highlight_query/ruby_highlights.scm
pyvi_editor/highlight_query/rust_highlights.scm
pyvi_editor/highlight_query/typescript_highlights.scm
pyvi_editor/key_binding.py
pyvi_editor/main.py
pyvi_editor/store/settings.ini
pyvi_editor/store/stores.ini
pyvi_editor/styles/style.tcss
pyvi_editor/syntax_highlighting.py
pyvi_editor/utils.py
pyvi_editor-0.1.0.dist-info/METADATA
pyvi_editor-0.1.0.dist-info/WHEEL
pyvi_editor-0.1.0.dist-info/entry_points.txt
pyvi_editor-0.1.0.dist-info/RECORD
