Metadata-Version: 2.1
Name: pyvi-editor
Version: 0.1.0
Summary: 
Author: MuongKimhong
Author-email: muongkimhong086@gmail.com
Requires-Python: >=3.11,<4.0
Classifier: Programming Language :: Python :: 3
Classifier: Programming Language :: Python :: 3.11
Classifier: Programming Language :: Python :: 3.12
Requires-Dist: numpy (>=1.26.3,<2.0.0)
Requires-Dist: textual (>=0.47.1,<0.48.0)
Requires-Dist: textual-dev (>=1.4.0,<2.0.0)
Requires-Dist: tree-sitter-languages (>=1.9.1,<2.0.0)
